{
  "supplier_id": "SUP007",
  "supplier_name": "Hernandez, Gonzalez and Curry",
  "order_date": "2025-12-02",
  "total_items": 4,
  "total_value": 785.9200000000001,
  "generated_at": "2026-01-04T10:27:12.219094",
  "items": [
    {
      "order_id": "f17bc328-7f60-4b07-ac72-1af6e3352acd",
      "order_date": "2025-12-02",
      "supplier_id": "SUP007",
      "supplier_name": "Hernandez, Gonzalez and Curry",
      "sku_id": "SKU000144",
      "product_name": "Least Dairy Gold",
      "demand": 34,
      "available_stock": 43,
      "reserved_stock": 0,
      "safety_stock": 10,
      "net_demand": 1,
      "order_quantity": 6,
      "pack_size": 6,
      "unit_price": 18.57,
      "total_price": 111.42,
      "lead_time_days": 5,
      "calculated_at": "2026-01-04T10:27:12.199905"
    },
    {
      "order_id": "ba493940-75c8-42e7-a3af-7cdbaf2302fd",
      "order_date": "2025-12-02",
      "supplier_id": "SUP007",
      "supplier_name": "Hernandez, Gonzalez and Curry",
      "sku_id": "SKU000213",
      "product_name": "Sea Bakery Basic",
      "demand": 55,
      "available_stock": 50,
      "reserved_stock": 0,
      "safety_stock": 10,
      "net_demand": 15,
      "order_quantity": 15,
      "pack_size": 1,
      "unit_price": 18.01,
      "total_price": 270.15000000000003,
      "lead_time_days": 5,
      "calculated_at": "2026-01-04T10:27:12.200101"
    },
    {
      "order_id": "6428d6bd-9786-4c03-a262-39d4a1d79657",
      "order_date": "2025-12-02",
      "supplier_id": "SUP007",
      "supplier_name": "Hernandez, Gonzalez and Curry",
      "sku_id": "SKU000245",
      "product_name": "Figure Beverages Basic",
      "demand": 51,
      "available_stock": 50,
      "reserved_stock": 0,
      "safety_stock": 10,
      "net_demand": 11,
      "order_quantity": 11,
      "pack_size": 1,
      "unit_price": 15.53,
      "total_price": 170.82999999999998,
      "lead_time_days": 2,
      "calculated_at": "2026-01-04T10:27:12.200201"
    },
    {
      "order_id": "9e909b2f-473d-469b-af30-97d77d52d020",
      "order_date": "2025-12-02",
      "supplier_id": "SUP007",
      "supplier_name": "Hernandez, Gonzalez and Curry",
      "sku_id": "SKU000309",
      "product_name": "Visit Personal Care Pro",
      "demand": 42,
      "available_stock": 50,
      "reserved_stock": 0,
      "safety_stock": 10,
      "net_demand": 2,
      "order_quantity": 24,
      "pack_size": 24,
      "unit_price": 9.73,
      "total_price": 233.52,
      "lead_time_days": 5,
      "calculated_at": "2026-01-04T10:27:12.200401"
    }
  ]
}