{
  "supplier_id": "SUP002",
  "supplier_name": "Kennedy-Liu",
  "order_date": "2025-12-02",
  "total_items": 2,
  "total_value": 266.1,
  "generated_at": "2026-01-10T20:43:30.688757",
  "items": [
    {
      "order_id": "365f46e6-ef75-42b8-8653-d103f88c54e2",
      "order_date": "2025-12-02",
      "supplier_id": "SUP002",
      "supplier_name": "Kennedy-Liu",
      "sku_id": "SKU000181",
      "product_name": "Free Grocery Organic",
      "demand": 41,
      "available_stock": 50,
      "reserved_stock": 0,
      "safety_stock": 10,
      "net_demand": 1,
      "order_quantity": 10,
      "pack_size": 1,
      "unit_price": 16.92,
      "total_price": 169.20000000000002,
      "lead_time_days": 3,
      "calculated_at": "2026-01-10T20:43:30.455771",
      "calculation_details": {
        "formula": "max(0, demand + safety_stock - available_stock)",
        "demand": 41,
        "safety_stock": 10,
        "available_stock": 50,
        "calculation": "max(0, 41 + 10 - 50) = 1"
      }
    },
    {
      "order_id": "8739ca25-aa51-4eec-b205-60d76604c342",
      "order_date": "2025-12-02",
      "supplier_id": "SUP002",
      "supplier_name": "Kennedy-Liu",
      "sku_id": "SKU000495",
      "product_name": "Forward Bakery Pro",
      "demand": 44,
      "available_stock": 50,
      "reserved_stock": 0,
      "safety_stock": 10,
      "net_demand": 4,
      "order_quantity": 6,
      "pack_size": 6,
      "unit_price": 16.15,
      "total_price": 96.89999999999999,
      "lead_time_days": 4,
      "calculated_at": "2026-01-10T20:43:30.644576",
      "calculation_details": {
        "formula": "max(0, demand + safety_stock - available_stock)",
        "demand": 44,
        "safety_stock": 10,
        "available_stock": 50,
        "calculation": "max(0, 44 + 10 - 50) = 4"
      }
    }
  ]
}